[
  {
    "timestamp": "2026-06-14T12:00:00Z",
    "event_type": "authentication",
    "source_ip": "192.0.2.1",
    "username": "admin",
    "action": "login",
    "outcome": "failure",
    "reason": "invalid_password",
    "user_agent": "Mozilla/5.0 (Windows NT 10.0; Win64; x64) AppleWebKit/537.36"
  },
  {
    "timestamp": "2026-06-14T12:01:00Z",
    "event_type": "authentication",
    "source_ip": "192.0.2.2",
    "username": "admin",
    "action": "login",
    "outcome": "failure",
    "reason": "invalid_password",
    "user_agent": "Mozilla/5.0 (Macintosh; Intel Mac OS X 10_15_7) AppleWebKit/537.36"
  },
  {
    "timestamp": "2026-06-14T12:02:00Z",
    "event_type": "authentication",
    "source_ip": "192.0.2.3",
    "username": "admin",
    "action": "login",
    "outcome": "failure",
    "reason": "invalid_password",
    "user_agent": "Mozilla/5.0 (X11; Linux x86_64) AppleWebKit/537.36"
  },
  {
    "timestamp": "2026-06-14T12:03:00Z",
    "event_type": "authentication",
    "source_ip": "192.0.2.4",
    "username": "admin",
    "action": "login",
    "outcome": "success",
    "reason": "mfa_bypass",
    "user_agent": "Mozilla/5.0 (Windows NT 10.0; Win64; x64) AppleWebKit/537.36"
  }
]
